RobotGraph/__init__.py
RobotGraph/__main__.py
RobotGraph/gen_graph.py
RobotGraph/mermaid.min.js
RobotGraph/template.html
robotframework_resource_graph-1.1.0.dist-info/entry_points.txt
robotframework_resource_graph-1.1.0.dist-info/WHEEL
robotframework_resource_graph-1.1.0.dist-info/METADATA
robotframework_resource_graph-1.1.0.dist-info/RECORD
