Metadata-Version: 2.1
Name: robotframework-resource-graph
Version: 1.1.0
Summary: Generate and visualize the dependency graph of Resource imports in Robot Framework
Author-email: Marduk Bolanos <mardukbp@mac.com>
Requires-Python: >=3.8
Requires-Dist: robotframework>=7.0.1
